{
  "n_samples": 20000,
  "batch_size": 64,
  "gen_embedding_dim": 64,
  "gen_hidden_dim" : 64,
  "dis_embedding_dim": 64,
  "dis_hidden_dim": 64,

  "file_path": "./data/train.csv",
  "dataset_features": ["srcip", "sport", "dstip", "dsport", "proto", "state", "dur", "sbytes",
                        "dbytes", "sttl", "dttl", "sloss", "dloss", "service", "sload", "dload",
                        "spkts", "dpkts", "swin", "dwin", "stcpb", "dtcpb", "smeansz",
                        "dmeansz", "trans_depth", "res_bdy_len", "sjit", "djit", "stime",
                        "ltime", "sintpkt", "dintpkt", "tcprtt", "synack", "ackdat",
                        "is_sm_ips_ports", "ct_state_ttl", "ct_flw_http_mthd", "is_ftp_login",
                        "ct_ftp_cmd", "ct_srv_src", "ct_srv_dst", "ct_dst_ltm", "ct_src_ltm",
                        "ct_src_dport_ltm", "ct_dst_sport_ltm", "ct_dst_src_ltm", "attack_cat",
                        "label"],
  "dataset_dtypes": {"srcip": "str",
                       "sport": "int32",
                       "dstip": "str",
                       "dsport": "int32",
                       "proto": "str",
                       "state": "str",
                       "dur": "float64",
                       "sbytes": "int32",
                       "dbytes": "int32",
                       "sttl": "int32",
                       "dttl": "int32",
                       "sloss": "int32",
                       "dloss": "int32",
                       "service": "str",
                       "sload": "float64",
                       "dload": "float64",
                       "spkts": "int32",
                       "dpkts": "int32",
                       "swin": "int32",
                       "dwin": "int32",
                       "stcpb": "int32",
                       "dtcpb": "int32",
                       "smeansz": "int32",
                       "dmeansz": "int32",
                       "trans_depth": "int32",
                       "res_bdy_len": "int32",
                       "sjit": "float64",
                       "djit": "float64",
                       "stime": "int",
                       "ltime": "int",
                       "sintpkt": "float64",
                       "dintpkt": "float64",
                       "tcprtt": "float64",
                       "synack": "float64",
                       "ackdat": "float64",
                       "attack_cat": "str",
                       "label": "int32"
                       },
  "generated_features": ["srcip", "dstip", "proto", "state", "service",
    "sport", "dsport", "spkts", "dpkts", "stime", "ltime", "attack_cat", "label"],



  "service_list": ["http", "ftp", "smtp", "ssh", "dns", "pop3", "dhcp", "snmp", "irc", "ssl"],
  "protocol_service_dict": {"tcp": ["http", "smtp", "ftp", "ssh", "pop3", "irc", "ssl"],
    "udp": ["dns", "dhcp", "snmp"]
  },
  "service_port_dict": {"http": [80],
  "ftp": [20, 21],
  "smtp": [25, 465, 587, 2525],
  "ssh": [22],
  "dns": [53],
  "pop3": [110, 995],
  "dhcp": [67, 68],
  "snmp": [161, 162],
  "irc": [6660, 6661, 6662, 6663, 6664, 6665, 6666, 6667, 6668, 6669, 6670],
  "ssl": [443]
  }
}
